MANIFEST.in
README.md
ez_setup.py
setup.cfg
setup.py
examples/client_get_by_email.py
examples/client_get_by_name_address.py
examples/client_get_by_phone.py
examples/client_get_by_profile_id.py
examples/client_get_fraud_level.py
examples/client_update_by_profile_id.py
examples/platform_create_platform_account.py
examples/platform_get_by_email.py
examples/platform_get_by_name_address.py
examples/platform_get_by_phone.py
examples/platform_get_by_profile_id.py
examples/platform_get_fraud_level.py
examples/platform_get_platform_account.py
examples/platform_get_statistics.py
examples/platform_update_by_profile_id.py
examples/platform_update_platform_account.py
pynextcaller/__init__.py
pynextcaller/auth.py
pynextcaller/client.py
pynextcaller/constants.py
pynextcaller/exceptions.py
pynextcaller/transport.py
pynextcaller/utils.py
pynextcaller.egg-info/PKG-INFO
pynextcaller.egg-info/SOURCES.txt
pynextcaller.egg-info/dependency_links.txt
pynextcaller.egg-info/requires.txt
pynextcaller.egg-info/top_level.txt
pynextcaller/tests/__init__.py
pynextcaller/tests/base.py
pynextcaller/tests/test_by_email.py
pynextcaller/tests/test_by_name_address.py
pynextcaller/tests/test_by_phone.py
pynextcaller/tests/test_by_profile.py
pynextcaller/tests/test_fraud.py
pynextcaller/tests/test_platform_statistics.py