Metadata-Version: 1.1
Name: pynextcaller
Version: 0.2
Summary: A Python wrapper around the Nextcaller API
Home-page: https://github.com/nextcaller/nextcaller-python-api.git
Author: Igor Nemilentsev
Author-email: trezorg@gmail.com
License: MIT
Keywords: nextcaller,python,api
Platform: UNKNOWN
Classifier: Development Status :: 4 - Beta
Classifier: Intended Audience :: Developers
Classifier: License :: OSI Approved :: MIT License
Classifier: Topic :: Software Development :: Libraries :: Python Modules
Classifier: Topic :: Communications
Classifier: Topic :: Internet
